README.rst
setup.py
leantesting/Client.py
leantesting/__init__.py
leantesting.egg-info/PKG-INFO
leantesting.egg-info/SOURCES.txt
leantesting.egg-info/dependency_links.txt
leantesting.egg-info/requires.txt
leantesting.egg-info/top_level.txt
leantesting/BaseClass/APIRequest.py
leantesting/BaseClass/Entity.py
leantesting/BaseClass/EntityHandler.py
leantesting/BaseClass/EntityList.py
leantesting/BaseClass/__init__.py
leantesting/Entity/__init__.py
leantesting/Entity/Bug/Bug.py
leantesting/Entity/Bug/BugAttachment.py
leantesting/Entity/Bug/BugComment.py
leantesting/Entity/Bug/__init__.py
leantesting/Entity/Platform/PlatformBrowser.py
leantesting/Entity/Platform/PlatformBrowserVersion.py
leantesting/Entity/Platform/PlatformDevice.py
leantesting/Entity/Platform/PlatformOS.py
leantesting/Entity/Platform/PlatformOSVersion.py
leantesting/Entity/Platform/PlatformType.py
leantesting/Entity/Platform/__init__.py
leantesting/Entity/Project/Project.py
leantesting/Entity/Project/ProjectBugScheme.py
leantesting/Entity/Project/ProjectSection.py
leantesting/Entity/Project/ProjectUser.py
leantesting/Entity/Project/ProjectVersion.py
leantesting/Entity/Project/__init__.py
leantesting/Entity/User/UserOrganization.py
leantesting/Entity/User/__init__.py
leantesting/Exception/SDKBadJSONResponseException.py
leantesting/Exception/SDKDuplicateRequestException.py
leantesting/Exception/SDKErrorResponseException.py
leantesting/Exception/SDKIncompleteRequestException.py
leantesting/Exception/SDKInvalidArgException.py
leantesting/Exception/SDKMissingArgException.py
leantesting/Exception/SDKUnexpectedResponseException.py
leantesting/Exception/SDKUnsupportedRequestException.py
leantesting/Exception/__init__.py
leantesting/Exception/BaseException/SDKException.py
leantesting/Exception/BaseException/__init__.py
leantesting/Handler/__init__.py
leantesting/Handler/Attachment/AttachmentsHandler.py
leantesting/Handler/Attachment/__init__.py
leantesting/Handler/Auth/OAuth2Handler.py
leantesting/Handler/Auth/__init__.py
leantesting/Handler/Bug/BugAttachmentsHandler.py
leantesting/Handler/Bug/BugCommentsHandler.py
leantesting/Handler/Bug/BugsHandler.py
