Metadata-Version: 1.1
Name: leantesting
Version: 1.2.0
Summary: Lean Testing Python SDK
Home-page: https://github.com/crowdsourcedtesting/leantesting-python
Author: Lean Testing
Author-email: support@crowdsourcedtesting.com
License: MIT
Keywords: development api bug tracker
Platform: UNKNOWN
Classifier: Development Status :: 5 - Production/Stable
Classifier: Intended Audience :: Developers
Classifier: Topic :: Software Development :: Build Tools
Classifier: License :: Other/Proprietary License
Classifier: Programming Language :: Python :: 3
Classifier: Programming Language :: Python :: 3.2
Classifier: Programming Language :: Python :: 3.3
Classifier: Programming Language :: Python :: 3.4
